hysen/__init__.py
hysen/hysen2pfc.py
hysen/hysendevice.py
hysen/hysenheating.py
hysen-0.4.12.dist-info/LICENSE
hysen-0.4.12.dist-info/METADATA
hysen-0.4.12.dist-info/WHEEL
hysen-0.4.12.dist-info/top_level.txt
hysen-0.4.12.dist-info/RECORD
