Metadata-Version: 2.1
Name: hysen
Version: 0.4.12
Summary: Python API for controlling Hysen thermostats
Home-page: http://github.com/uspass/hysen
Author: us
License: UNKNOWN
Platform: UNKNOWN
Classifier: Programming Language :: Python :: 3
Classifier: License :: OSI Approved :: MIT License
Classifier: Operating System :: OS Independent
Classifier: Intended Audience :: Developers
Classifier: Development Status :: 4 - Beta
Classifier: Natural Language :: English
License-File: LICENSE
Requires-Dist: broadlink (==0.18.0)
